{
  "color-primary-100": "#FCDDD1",
  "color-primary-200": "#FAB5A5",
  "color-primary-300": "#F28276",
  "color-primary-400": "#E55453",
  "color-primary-500": "#D4202F",
  "color-primary-600": "#B61733",
  "color-primary-700": "#981034",
  "color-primary-800": "#7A0A32",
  "color-primary-900": "#650630",
  "color-success-100": "#E9FBD4",
  "color-success-200": "#CEF8AA",
  "color-success-300": "#A7EA7C",
  "color-success-400": "#81D658",
  "color-success-500": "#4EBC29",
  "color-success-600": "#35A11D",
  "color-success-700": "#218714",
  "color-success-800": "#106D0D",
  "color-success-900": "#075A0A",
  "color-info-100": "#CBFAFE",
  "color-info-200": "#98EFFD",
  "color-info-300": "#64DDFB",
  "color-info-400": "#3EC6F8",
  "color-info-500": "#00A3F4",
  "color-info-600": "#007ED1",
  "color-info-700": "#005EAF",
  "color-info-800": "#00438D",
  "color-info-900": "#003075",
  "color-warning-100": "#FDF6CA",
  "color-warning-200": "#FBEB96",
  "color-warning-300": "#F4D961",
  "color-warning-400": "#EAC63A",
  "color-warning-500": "#DDAA00",
  "color-warning-600": "#BE8D00",
  "color-warning-700": "#9F7200",
  "color-warning-800": "#805900",
  "color-warning-900": "#6A4700",
  "color-danger-100": "#FEE5D2",
  "color-danger-200": "#FDC5A6",
  "color-danger-300": "#FB9D78",
  "color-danger-400": "#F77657",
  "color-danger-500": "#F23A21",
  "color-danger-600": "#D01F18",
  "color-danger-700": "#AE1016",
  "color-danger-800": "#8C0A1A",
  "color-danger-900": "#74061C"
}